vc/__init__.py
vc/__main__.py
vc/main.py
vc/util.py
video_compress-0.3.0.dist-info/METADATA
video_compress-0.3.0.dist-info/WHEEL
video_compress-0.3.0.dist-info/entry_points.txt
video_compress-0.3.0.dist-info/licenses/LICENSE
video_compress-0.3.0.dist-info/RECORD
