Metadata-Version: 2.3
Name: video-compress
Version: 0.3.0
Summary: Compress video by 90% without losing much quality, similar to what Pied Piper achieves.
Project-URL: Repository, https://github.com/jiacai2050/video-compress
Project-URL: Issues, https://github.com/jiacai2050/video-compress/issues
Author-email: Jiacai Liu <dev@liujiacai.net>
License-Expression: GPL-3.0
License-File: LICENSE
Keywords: compress,ffmpeg,videos
Classifier: Intended Audience :: Developers
Classifier: Intended Audience :: Information Technology
Classifier: Intended Audience :: System Administrators
Classifier: License :: OSI Approved :: GNU General Public License v3 (GPLv3)
Classifier: Operating System :: OS Independent
Classifier: Programming Language :: Python :: 3.6
Classifier: Programming Language :: Python :: 3.7
Classifier: Programming Language :: Python :: 3.8
Classifier: Programming Language :: Python :: 3.9
Classifier: Programming Language :: Python :: 3.10
Classifier: Programming Language :: Python :: 3.11
Classifier: Topic :: Software Development
Requires-Python: >=3.6.0
